intentusnet/__init__.py
intentusnet/adapters/mcp_adapter.py
intentusnet/cli/__init__.py
intentusnet/cli/agent_commands.py
intentusnet/cli/commands.py
intentusnet/cli/contract_commands.py
intentusnet/cli/cost_commands.py
intentusnet/cli/execution_commands.py
intentusnet/cli/main.py
intentusnet/cli/main_old.py
intentusnet/cli/output.py
intentusnet/cli/record_commands.py
intentusnet/cli/security.py
intentusnet/cli/wal_commands.py
intentusnet/contracts/__init__.py
intentusnet/contracts/enforcement.py
intentusnet/contracts/models.py
intentusnet/contracts/validator.py
intentusnet/core/agent.py
intentusnet/core/client.py
intentusnet/core/deterministic_router.py
intentusnet/core/logging_config.py
intentusnet/core/middleware.py
intentusnet/core/registry.py
intentusnet/core/remote_agent.py
intentusnet/core/router.py
intentusnet/core/runtime.py
intentusnet/core/settings.py
intentusnet/core/telemetry.py
intentusnet/core/tracing.py
intentusnet/estimation/__init__.py
intentusnet/estimation/estimator.py
intentusnet/estimation/models.py
intentusnet/failures/__init__.py
intentusnet/failures/models.py
intentusnet/failures/registry.py
intentusnet/intentus-cli/intentus/__main__.py
intentusnet/intentus-cli/intentus/cli.py
intentusnet/intentus-cli/intentus/commands/agents.py
intentusnet/intentus-cli/intentus/commands/config.py
intentusnet/intentus-cli/intentus/commands/intent.py
intentusnet/intentus-cli/intentus/commands/trace.py
intentusnet/observability/__init__.py
intentusnet/observability/health.py
intentusnet/observability/metrics.py
intentusnet/observability/server.py
intentusnet/protocol/__init__.py
intentusnet/protocol/agent.py
intentusnet/protocol/codec.py
intentusnet/protocol/emcl.py
intentusnet/protocol/enums.py
intentusnet/protocol/errors.py
intentusnet/protocol/identity_chain.py
intentusnet/protocol/intent.py
intentusnet/protocol/response.py
intentusnet/protocol/tracing.py
intentusnet/protocol/transport.py
intentusnet/protocol/validators.py
intentusnet/recording/__init__.py
intentusnet-1.3.0.dist-info/licenses/LICENSE
intentusnet-1.3.0.dist-info/METADATA
intentusnet-1.3.0.dist-info/WHEEL
intentusnet-1.3.0.dist-info/entry_points.txt
intentusnet-1.3.0.dist-info/top_level.txt
intentusnet-1.3.0.dist-info/RECORD
