Metadata-Version: 2.4
Name: intentusnet
Version: 1.3.0
Summary: IntentusNet is a deterministic AI intent routing and execution runtime that makes LLM-driven systems inspectable, replayable, and failure-safe.
Author: Balachandar Manikandan
License: MIT License
Keywords: agents,router,intent-routing,runtime,mcp,distributed-agents
Classifier: Programming Language :: Python :: 3
Classifier: Operating System :: OS Independent
Classifier: License :: OSI Approved :: MIT License
Requires-Python: >=3.9
License-File: LICENSE
Requires-Dist: cryptography>=42.0.0
Requires-Dist: websockets>=12.0
Requires-Dist: pyzmq>=25.1.0
Requires-Dist: fastapi>=0.110.0
Requires-Dist: uvicorn>=0.29.0
Requires-Dist: python-dateutil>=2.9.0.post0
Provides-Extra: dev
Requires-Dist: pytest>=7.4.0; extra == "dev"
Requires-Dist: pytest-asyncio>=0.23.0; extra == "dev"
Requires-Dist: mypy>=1.8.0; extra == "dev"
Requires-Dist: black>=24.1.1; extra == "dev"
Requires-Dist: ruff>=0.2.0; extra == "dev"
Provides-Extra: examples
Requires-Dist: requests>=2.31.0; extra == "examples"
Requires-Dist: aiohttp>=3.9.1; extra == "examples"
Dynamic: license-file
